CHANGES.txt
README.txt
setup.py
cornerstone/__init__.py
cornerstone.ui.result.egg-info/PKG-INFO
cornerstone.ui.result.egg-info/SOURCES.txt
cornerstone.ui.result.egg-info/dependency_links.txt
cornerstone.ui.result.egg-info/entry_points.txt
cornerstone.ui.result.egg-info/namespace_packages.txt
cornerstone.ui.result.egg-info/not-zip-safe
cornerstone.ui.result.egg-info/requires.txt
cornerstone.ui.result.egg-info/top_level.txt
cornerstone/ui/__init__.py
cornerstone/ui/result/__init__.py
cornerstone/ui/result/batch.py
cornerstone/ui/result/configure.zcml
cornerstone/ui/result/interfaces.py
cornerstone/ui/result/meta.zcml
cornerstone/ui/result/metaconfigure.py
cornerstone/ui/result/metadirectives.py
cornerstone/ui/result/profiles.zcml
cornerstone/ui/result/result.py
cornerstone/ui/result/slice.py
cornerstone/ui/result/css/result.css
cornerstone/ui/result/images/left.gif
cornerstone/ui/result/images/left_invisible.gif
cornerstone/ui/result/images/leftmost.gif
cornerstone/ui/result/images/leftmost_invisible.gif
cornerstone/ui/result/images/right.gif
cornerstone/ui/result/images/right_invisible.gif
cornerstone/ui/result/images/rightmost.gif
cornerstone/ui/result/images/rightmost_invisible.gif
cornerstone/ui/result/profiles/default/cssregistry.xml
cornerstone/ui/result/profiles/default/kssregistry.xml
cornerstone/ui/result/profiles/default/metadata.xml
cornerstone/ui/result/resultkss/__init__.py
cornerstone/ui/result/resultkss/browser.py
cornerstone/ui/result/resultkss/configure.zcml
cornerstone/ui/result/resultkss/cornerstone.ui.result.kss
cornerstone/ui/result/templates/ascii_batch.pt
cornerstone/ui/result/templates/batch.pt
cornerstone/ui/result/tests/__init__.py
cornerstone/ui/result/tests/configure.zcml
cornerstone/ui/result/tests/env.py
cornerstone/ui/result/tests/results.zcml
cornerstone/ui/result/tests/run.py
cornerstone/ui/result/tests/templates/batch.pt