Metadata-Version: 1.0
Name: cornerstone.ui.result
Version: 1.1.4
Summary: library providing a result rendering engine
Home-page: UNKNOWN
Author: Robert Niedereiter
Author-email: rnix@squarewave.at
License: License :: OSI Approved :: Zope Public License
Platform: UNKNOWN
Classifier: Development Status :: 5 - Production/Stable
Classifier: Environment :: Web Environment
Classifier: Framework :: Zope2
Classifier: License :: OSI Approved :: Zope Public License
Classifier: Operating System :: OS Independent
Classifier: Programming Language :: Python
Classifier: Topic :: Internet :: WWW/HTTP :: Dynamic Content
